ffctl/__init__.py
ffctl/utils.py
ffctl/commands/__init__.py
ffctl/commands/cli.py
ffctl/commands/command_base.py
ffctl/commands/generate.py
ffctl/commands/lint.py
ffctl/commands/version.py
ffctl-0.2.0.data/scripts/ffctl
ffctl-0.2.0.dist-info/DESCRIPTION.rst
ffctl-0.2.0.dist-info/METADATA
ffctl-0.2.0.dist-info/RECORD
ffctl-0.2.0.dist-info/WHEEL
ffctl-0.2.0.dist-info/metadata.json
ffctl-0.2.0.dist-info/top_level.txt
