Metadata-Version: 2.0
Name: ffctl
Version: 0.2.0
Summary: ffctl cli
Home-page: https://github.com/ant31/ffctl
Author: Antoine Legrand
Author-email: 2t.antoine@gmail.com
License: Apache License version 2
Keywords: ffctl,ffctlpy,kubernetes
Platform: UNKNOWN
Classifier: Development Status :: 2 - Pre-Alpha
Classifier: Intended Audience :: Developers
Classifier: Natural Language :: English
Classifier: Programming Language :: Python :: 2
Classifier: Programming Language :: Python :: 2.7
Requires-Dist: futures
Requires-Dist: pyyaml
Requires-Dist: pyjsonnet (>=0.0.4)
Requires-Dist: requests
Requires-Dist: jinja2 (>=2.8)
